ordeq_plotly_express/__init__.py
ordeq_plotly_express/_version.py
ordeq_plotly_express/figure.py
ordeq_plotly_express/py.typed
ordeq_plotly_express-0.1.0.dist-info/licenses/LICENSE
ordeq_plotly_express-0.1.0.dist-info/METADATA
ordeq_plotly_express-0.1.0.dist-info/WHEEL
ordeq_plotly_express-0.1.0.dist-info/top_level.txt
ordeq_plotly_express-0.1.0.dist-info/RECORD
