Metadata-Version: 2.4
Name: ordeq_plotly_express
Version: 0.1.0
Summary: Plotly Express integration for Ordeq
Author: Niels Neerhoff, Simon Brugman
Maintainer: Niels Neerhoff, Simon Brugman
License-Expression: MIT
Requires-Python: >=3.10
License-File: LICENSE
Requires-Dist: ordeq>=1.2.0
Requires-Dist: plotly-express
Dynamic: license-file
